[{"name": 1, "count": 366, "probability": 0.044677734375}, {"name": 2, "count": 1201, "probability": 0.1466064453125}, {"name": 3, "count": 1882, "probability": 0.229736328125}, {"name": 4, "count": 1908, "probability": 0.23291015625}, {"name": 5, "count": 1396, "probability": 0.17041015625}, {"name": 6, "count": 870, "probability": 0.106201171875}, {"name": 7, "count": 375, "probability": 0.0457763671875}, {"name": 8, "count": 153, "probability": 0.0186767578125}, {"name": 9, "count": 37, "probability": 0.0045166015625}, {"name": 10, "count": 4, "probability": 0.00048828125}]